codecov/__init__.py
codecov/__main__.py
codecov/__version__.py
codecov-2.1.12.dist-info/LICENSE
codecov-2.1.12.dist-info/METADATA
codecov-2.1.12.dist-info/WHEEL
codecov-2.1.12.dist-info/entry_points.txt
codecov-2.1.12.dist-info/top_level.txt
codecov-2.1.12.dist-info/zip-safe
codecov-2.1.12.dist-info/RECORD
